.gitignore
.readthedocs.yml
CHANGES.rst
CITATION.cff
DEVELOPER_DOC.rst
MANIFEST.in
README.rst
pyproject.toml
setup.cfg
setup.py
tox.ini
.github/CODEOWNERS
.github/dependabot.yml
.github/workflows/black.yml
.github/workflows/ci_workflows.yml
astronify/__init__.py
astronify/_astropy_init.py
astronify/_compiler.c
astronify/conftest.py
astronify/example_c.c
astronify/version.py
astronify.egg-info/PKG-INFO
astronify.egg-info/SOURCES.txt
astronify.egg-info/dependency_links.txt
astronify.egg-info/entry_points.txt
astronify.egg-info/not-zip-safe
astronify.egg-info/requires.txt
astronify.egg-info/top_level.txt
astronify/data/README.rst
astronify/series/__init__.py
astronify/series/series.py
astronify/series/tests/__init__.py
astronify/series/tests/test_series.py
astronify/simulator/__init__.py
astronify/simulator/add_flare_signal.py
astronify/simulator/add_lc_noise.py
astronify/simulator/add_sine_signal.py
astronify/simulator/add_transit_signal.py
astronify/simulator/check_flare_params.py
astronify/simulator/check_transit_params.py
astronify/simulator/example_cmds.sh
astronify/simulator/make_wavs.py
astronify/simulator/sim_lc.py
astronify/simulator/sim_lc_config.py
astronify/simulator/sim_lc_setup_args.py
astronify/simulator/z.py
astronify/utils/__init__.py
astronify/utils/exceptions.py
astronify/utils/pitch_mapping.py
astronify/utils/tests/__init__.py
astronify/utils/tests/test_pitch_mapping.py
docs/CreateWithLight.html
docs/Makefile
docs/conf.py
docs/contents.rst
docs/index.html
docs/make.bat
docs/requirements.txt
docs/_static/ASTRONIFY.svg
docs/_static/ASTRONIFY_Ball_white.svg
docs/_static/ASTRONIFY_white.png
docs/_static/ASTRONIFY_white.svg
docs/_static/BinaryPainting.png
docs/_static/Intro_Astronify_Series_6_0.png
docs/_static/astronify-CIRCLE.png
docs/_static/astronify-TEXT.png
docs/_static/astronify-favicon.png
docs/_static/astronify.css
docs/_static/kepler_12b.wav
docs/_static/main.css
docs/_templates/layout.html
docs/astronify/How_To_Use_The_Simulator.rst
docs/astronify/Intro_Astronify_Series.rst
docs/astronify/api.rst
docs/astronify/index.rst
docs/astronify/install.rst
docs/astronify/tutorials.rst
docs/astronify/How_To_Use_The_Simulator_files/How_To_Use_The_Simulator_12_0.png
