Metadata-Version: 2.2
Name: astronify
Version: 0.11
Summary: Sonification of astronomical data.
Home-page: https://github.com/spacetelescope/astronify
Author: Clara Brasseur, Scott Fleming, Jennifer Kotler, Kate Meredith, Pey-Lian Lim
Author-email: astronify@stsci.edu
License: BSD 3-Clause
Requires-Python: >=3.9
License-File: licenses/LICENSE.rst
Requires-Dist: astropy
Requires-Dist: scipy
Requires-Dist: matplotlib
Requires-Dist: pyo
Requires-Dist: requests
Requires-Dist: notebook
Provides-Extra: test
Requires-Dist: pytest-astropy; extra == "test"
Provides-Extra: docs
Requires-Dist: sphinx-astropy; extra == "docs"
